Metadata-Version: 1.0
Name: some-dist
Version: 0.1
Summary: Some distributions
Home-page: UNKNOWN
Author: UNKNOWN
Author-email: UNKNOWN
License: UNKNOWN
Platform: UNKNOWN
